argus/__init__.py
argus/calibrations.py
argus/cameras.py
argus/extrinsics.py
argus/offsets.py
argus/outputs.py
argus/version.py
argus/ocam/__init__.py
argus/ocam/base.py
argus-0.0.11.data/scripts/argus_align_combine
argus-0.0.11.data/scripts/argus_audio_sync2
argus-0.0.11.data/scripts/argus_detect_balls
argus-0.0.11.data/scripts/argus_detect_laser
argus-0.0.11.data/scripts/argus_detect_patterns
argus-0.0.11.data/scripts/argus_detect_patterns2
argus-0.0.11.data/scripts/argus_detect_wands
argus-0.0.11.data/scripts/argus_drop_rows
argus-0.0.11.data/scripts/argus_form_wands
argus-0.0.11.data/scripts/argus_initial_calibrate
argus-0.0.11.data/scripts/argus_initial_extrinsics
argus-0.0.11.data/scripts/argus_ocam_undistort
argus-0.0.11.data/scripts/argus_ocam_undistort2
argus-0.0.11.data/scripts/argus_ravel_easywand5
argus-0.0.11.data/scripts/argus_reconstruct
argus-0.0.11.data/scripts/argus_refine
argus-0.0.11.data/scripts/argus_select_points
argus-0.0.11.data/scripts/argus_simplified
argus-0.0.11.data/scripts/argus_summarize
argus-0.0.11.data/scripts/argus_to_DLTdv5
argus-0.0.11.data/scripts/argus_undistort
argus-0.0.11.dist-info/LICENSE.txt
argus-0.0.11.dist-info/METADATA
argus-0.0.11.dist-info/WHEEL
argus-0.0.11.dist-info/dependency_links.txt
argus-0.0.11.dist-info/top_level.txt
argus-0.0.11.dist-info/RECORD
