Metadata-Version: 2.1
Name: argus
Version: 0.0.11
Summary: Helper routines for using multiple, inexpensive calibrated and synchronized cameras for 3D scientific use.
Home-page: https://bitbucket.org/devangel77b/argus
Author: Brandon Jackson and Dennis Evangelista
Author-email: devangel77b@gmail.com
License: GNU GPLv3
Keywords: calibration,camera,camera calibration,photogrammetry
Platform: UNKNOWN
Classifier: Development Status :: 3 - Alpha
Classifier: Intended Audience :: Science/Research
Classifier: License :: OSI Approved :: GNU General Public License v3 (GPLv3)
Classifier: Operating System :: OS Independent
Classifier: Operating System :: POSIX :: Linux
Classifier: Programming Language :: Python :: 2.7
Classifier: Topic :: Multimedia :: Graphics
Classifier: Topic :: Multimedia :: Graphics :: 3D Modeling
Classifier: Topic :: Multimedia :: Graphics :: Capture :: Digital Camera
Classifier: Topic :: Multimedia :: Video
Classifier: Topic :: Scientific/Engineering
Requires-Dist: numpy (>=1.13.0)
Requires-Dist: pandas (>=0.20.2)
Requires-Dist: scipy (>=0.19.1)
